streamlit_blockly/__init__.py
streamlit_blockly/config.py
streamlit_blockly/streamlit/__init__.py
streamlit_blockly/streamlit/base.py
streamlit_blockly/streamlit/static/index.html
streamlit_blockly/streamlit/static/assets/index-BHPerQp4.js
streamlit_blockly/streamlit/static/assets/index-CBDzt8PV.css
streamlit_blockly-0.0.2.dist-info/LICENSE
streamlit_blockly-0.0.2.dist-info/METADATA
streamlit_blockly-0.0.2.dist-info/WHEEL
streamlit_blockly-0.0.2.dist-info/top_level.txt
streamlit_blockly-0.0.2.dist-info/RECORD
