Metadata-Version: 2.2
Name: streamlit-blockly
Version: 0.0.2
Summary: A Streamlit component for Google Blockly
Author-email: Hasan Iqbal <hasan.iqbal@mbzuai.ac.ae>
Maintainer-email: Hasan Iqbal <hasan.iqbal@mbzuai.ac.ae>
License:                                  Apache License
Keywords: streamlit,blockly,google,component
Classifier: Development Status :: 3 - Alpha
Classifier: Intended Audience :: Developers
Classifier: Intended Audience :: Education
Classifier: Intended Audience :: Science/Research
Classifier: License :: OSI Approved :: GNU General Public License v3 (GPLv3)
Classifier: Operating System :: OS Independent
Classifier: Programming Language :: Python :: 3
Classifier: Topic :: Scientific/Engineering :: Artificial Intelligence
Requires-Python: >=3.10
License-File: LICENSE
